{"cameraMode":{"drawMode":0,"name":"Shaded","section":"Shading Mode"},"sceneLighting":true,"audioPlay":false,"sceneViewState":{"showFog":true,"showMaterialUpdate":false,"showSkybox":true,"showFlares":true,"showImageEffects":true,"showParticleSystems":true},"in2DMode":false,"pivot":{"x":1.1465198993682862,"y":7.898381233215332,"z":-22.224491119384767},"rotation":{"x":-0.00749807758256793,"y":-0.022497501224279405,"z":-0.00016860025061760098,"w":0.9997214078903198},"size":1.8247449398040772,"orthographic":false}